geoget/__init__.py
geoget/_nbdev.py
geoget/cli.py
geoget/core.py
geoget/download.py
geoget/era5.py
geoget/external.py
geoget/geo.py
geoget/gfs.py
geoget-0.1.17.dist-info/LICENSE
geoget-0.1.17.dist-info/METADATA
geoget-0.1.17.dist-info/WHEEL
geoget-0.1.17.dist-info/entry_points.txt
geoget-0.1.17.dist-info/top_level.txt
geoget-0.1.17.dist-info/RECORD
