Metadata-Version: 2.1
Name: geoget
Version: 0.1.17
Summary: Download geodata for anywhere in Earth
Home-page: https://github.com/mnpinto/geoget
Author: Miguel Pinto
Author-email: mnpinto@fc.ul.pt
License: Apache Software License 2.0
Keywords: remote sensing,geodata,download utility
Platform: UNKNOWN
Classifier: Development Status :: 4 - Beta
Classifier: Intended Audience :: Science/Research
Classifier: License :: OSI Approved :: Apache Software License
Classifier: Natural Language :: English
Classifier: Programming Language :: Python :: 3.6
Classifier: Programming Language :: Python :: 3.7
Classifier: Programming Language :: Python :: 3.8
Requires-Python: >=3.6
License-File: LICENSE
Requires-Dist: matplotlib
Requires-Dist: fastscript
Requires-Dist: fastprogress
Requires-Dist: netcdf4
Requires-Dist: rasterio
Requires-Dist: geopandas
Requires-Dist: tqdm
Requires-Dist: requests
Requires-Dist: cdsapi
